{
  "kb_name": "fliggy-hotel-package-kb",
  "created_at": "2026-04-14T19:35:00Z",
  "last_updated": "2026-04-14T20:15:00Z",
  "domain": "飞猪酒店套餐产品",
  "product_scope": "频道页 → 酒店日历页 → 套餐详情页 → 套餐SKU浮层 → 下单页",
  "core_goal": "提升D2O转化率",
  "sources": [
    {
      "name": "套餐各叶子类目id",
      "type": "dingtalk_doc",
      "url": "https://alidocs.dingtalk.com/i/nodes/93NwLYZXWyZPdyb1CdZ6Xo47VkyEqBQm",
      "raw_file": "raw/dingtalk-93NwLYZXWyZPdyb1CdZ6Xo47VkyEqBQm.md",
      "ingested_at": "2026-04-14T19:45:00Z"
    },
    {
      "name": "套餐详情页模块结构",
      "type": "user_input",
      "raw_file": "raw/detail-page-modules-structure.md",
      "ingested_at": "2026-04-14T20:00:00Z"
    },
    {
      "name": "心智区支持业务自定义配置亮点标签",
      "type": "dingtalk_doc",
      "url": "https://alidocs.dingtalk.com/i/nodes/kDnRL6jAJMpxeYDohKK2m1YyVyMoPYe1",
      "pm": "宁音",
      "raw_file": "raw/dingtalk-kDnRL6jAJMpxeYDohKK2m1YyVyMoPYe1.md",
      "ingested_at": "2026-04-14T20:15:00Z"
    },
    {
      "name": "业务语义字典与服务标签补充",
      "type": "user_input",
      "raw_file": "raw/user-input-semantics-and-tags.md",
      "ingested_at": "2026-04-14T20:15:00Z"
    }
  ],
  "stats": {
    "total_pages": 32,
    "total_sources": 4,
    "entities": 21,
    "concepts": 3,
    "topics": 0,
    "completed_modules": 1
  },
  "pending_tasks": [
    "补充详情页其余13个模块详细信息",
    "完善各类目支持的预约方式"
  ],
  "git_repo": "https://github.com/mai-hub-ai/knowledge-bases.git"
}
